[
  {
    "title": "LINEA DE ANTEOJOS ARGON GRIS HC",
    "imageURL": "https://www.corcelsafety.com.ar/contenido/productos/thumb_800_600/1669383981.png",
    "category": "Anteojos"
  },
  {
    "title": "ANTEOJO ECOLINE GRIS HC",
    "imageURL": "https://www.corcelsafety.com.ar/contenido/productos/thumb_800_600/1669383723.png",
    "category": "Anteojos"
  },
  {
    "title": "LINEA DE ANTEOJOS ECOLINE TRANSP HC",
    "imageURL": "https://www.corcelsafety.com.ar/contenido/productos/thumb_800_600/1669383899.png",
    "category": "Anteojos"
  },
  {
    "title": "LÍNEA DE ANTEOJOS ECOLINE TRANSP AF",
    "imageURL": "https://www.corcelsafety.com.ar/contenido/productos/thumb_800_600/1669384032.png",
    "category": "Anteojos"
  },
  {
    "title": "LÍNEA DE ANTEOJOS IMPACT",
    "imageURL": "https://www.corcelsafety.com.ar/contenido/productos/thumb_800_600/1606929822.jpeg",
    "category": "Anteojos"
  },
  {
    "title": "ANTIPARRA FLIP UP",
    "imageURL": "https://www.corcelsafety.com.ar/contenido/productos/thumb_800_600/1669384213.png",
    "category": "Anteojos"
  },
  {
    "title": "LÍNEA DE ANTEOJOS HAYAT",
    "imageURL": "https://www.corcelsafety.com.ar/contenido/productos/thumb_800_600/1606932135.jpeg",
    "category": "Anteojos"
  },
  {
    "title": "LÍNEA DE ANTEOJOS URANO",
    "imageURL": "https://www.corcelsafety.com.ar/contenido/productos/thumb_800_600/1606931810.jpeg",
    "category": "Anteojos"
  },
  {
    "title": "LÍNEA DE ANTEOJOS FALL DUAL",
    "imageURL": "https://www.corcelsafety.com.ar/contenido/productos/thumb_800_600/1669383800.png",
    "category": "Anteojos"
  },
  {
    "title": "LÍNEA DE ANTEOJOS ARGON AF",
    "imageURL": "https://www.corcelsafety.com.ar/contenido/productos/thumb_800_600/1606922569.jpeg",
    "category": "Anteojos"
  },
  {
    "title": "LINEA DE ANTEOJOS ARGON TRANSPARENTE HC",
    "imageURL": "https://www.corcelsafety.com.ar/contenido/productos/thumb_800_600/1669384266.png",
    "category": "Anteojos"
  },
  {
    "title": "LÍNEA DE ANTEOJOS ECO PLUS",
    "imageURL": "https://www.corcelsafety.com.ar/contenido/productos/thumb_800_600/1604867962.png",
    "category": "Anteojos"
  },
  {
    "title": "LÍNEA DE ANTEOJOS ARGON ELITE",
    "imageURL": "https://www.corcelsafety.com.ar/contenido/productos/thumb_800_600/1606922625.jpeg",
    "category": "Anteojos"
  },
  {
    "title": "LÍNEA DE ANTIPARRAS NEW CLASSIC HC TRANSPARENTE",
    "imageURL": "https://www.corcelsafety.com.ar/contenido/productos/thumb_800_600/1604878737.png",
    "category": "Anteojos"
  },
  {
    "title": "LÍNEA DE ANTEOJOS KUBLAI",
    "imageURL": "https://www.corcelsafety.com.ar/contenido/productos/thumb_800_600/1606931699.jpeg",
    "category": "Anteojos"
  },
  {
    "title": "LÍNEA DE ANTEOJOS IRIS",
    "imageURL": "https://www.corcelsafety.com.ar/contenido/productos/thumb_800_600/1606930583.jpeg",
    "category": "Anteojos"
  },
  {
    "title": "LÍNEA DE ANTEOJOS MARVEL",
    "imageURL": "https://www.corcelsafety.com.ar/contenido/productos/thumb_800_600/1606931751.jpeg",
    "category": "Anteojos"
  },
  {
    "title": "LÍNEA DE ANTEOJOS DUAL RB",
    "imageURL": "https://www.corcelsafety.com.ar/contenido/productos/thumb_800_600/1669383536.png",
    "category": "Anteojos"
  },
  {
    "title": "LÍNEA DE ANTIPARRAS AVIATOR AF TRANSPARENTE",
    "imageURL": "https://www.corcelsafety.com.ar/contenido/productos/thumb_800_600/1604878642.png",
    "category": "Anteojos"
  },
  {
    "title": "LÍNEA DE ANTEOJOS SNOW - AF",
    "imageURL": "https://www.corcelsafety.com.ar/contenido/productos/thumb_800_600/1606930510.jpeg",
    "category": "Anteojos"
  },
  {
    "title": "ANTEOJO EVOLUTION TRANSPARENTE AF BLISTER",
    "imageURL": "https://www.corcelsafety.com.ar/contenido/productos/thumb_800_600/1606930318.jpeg",
    "category": "Anteojos"
  },
  {
    "title": "ANTEOJO ARGON TRANSPARENTE AF - BLISTER",
    "imageURL": "https://www.corcelsafety.com.ar/contenido/productos/thumb_800_600/1606930277.jpeg",
    "category": "Anteojos"
  },
  {
    "title": "LÍNEA DE ANTIPARRAS EXPLORER",
    "imageURL": "https://www.corcelsafety.com.ar/contenido/productos/thumb_800_600/1604878835.png",
    "category": "Anteojos"
  },
  {
    "title": "ANTEOJO LIBUS MODELO 904240",
    "imageURL": "https://www.corcelsafety.com.ar/contenido/productos/thumb_800_600/1604878518.png",
    "category": "Anteojos"
  }
]